fast_mq_task/__init__.py
fast_mq_task/client.py
fast_mq_task/consumer.py
fast_mq_task/decorators.py
fast_mq_task/exceptions.py
fast_mq_task/keys.py
fast_mq_task/models.py
fast_mq_task/producer.py
fast_mq_task/util.py
fast_mq_task-1.1.3.dist-info/METADATA
fast_mq_task-1.1.3.dist-info/WHEEL
fast_mq_task-1.1.3.dist-info/top_level.txt
fast_mq_task-1.1.3.dist-info/RECORD
